mysqldb_mcp_server/__init__.py
mysqldb_mcp_server/server.py
mysqldb_mcp_server-0.1.2.dist-info/METADATA
mysqldb_mcp_server-0.1.2.dist-info/WHEEL
mysqldb_mcp_server-0.1.2.dist-info/entry_points.txt
mysqldb_mcp_server-0.1.2.dist-info/licenses/LICENSE
mysqldb_mcp_server-0.1.2.dist-info/RECORD
